notion_logger/__init__.py
notion_logger-0.0.9.dist-info/LICENCE
notion_logger-0.0.9.dist-info/METADATA
notion_logger-0.0.9.dist-info/WHEEL
notion_logger-0.0.9.dist-info/top_level.txt
notion_logger-0.0.9.dist-info/RECORD
