Metadata-Version: 2.1
Name: notion-logger
Version: 0.0.9
Summary: A small logger for notion.so
Home-page: https://github.com/KamikottoGG/NotionLogger
Author: _Kamikotto_
Author-email: kamikotto3@gmail.com
Classifier: Programming Language :: Python :: 3
Classifier: License :: OSI Approved :: MIT License
Classifier: Operating System :: OS Independent
Requires-Python: >=3.10
License-File: LICENCE
Requires-Dist: requests
